[
    {
        "model": "user.User",
        "pk": 1,
        "fields": {
            "email": "webmaster@strom.sk",
            "password": "pbkdf2_sha256$180000$NyzwabHNPn2K$sTirqoFPMkLZpnUHkCpzUFZnAsbGM7Bp2+EoN8sOuQA=",
            "is_superuser": true,
            "is_staff": true,
            "groups": [
                1,
                2
            ]
        }
    },
    {
        "model": "personal.Profile",
        "pk": 1,
        "fields": {
            "user": 1,
            "first_name": "Webmaster",
            "last_name": "Strom",
            "school": 1,
            "year_of_graduation": 2000
        }
    },
    {
        "model": "account.emailaddress",
        "pk": 1,
        "fields": {
            "user": 1,
            "email": "webmaster@strom.sk",
            "verified": true,
            "primary": true
        }
    },
    {
        "model": "user.User",
        "pk": 2,
        "fields": {
            "email": "veduci_stromu@strom.sk",
            "password": "pbkdf2_sha256$180000$NyzwabHNPn2K$sTirqoFPMkLZpnUHkCpzUFZnAsbGM7Bp2+EoN8sOuQA=",
            "is_superuser": false,
            "is_staff": true,
            "groups": [
                1,
                2
            ]
        }
    },
    {
        "model": "personal.Profile",
        "pk": 2,
        "fields": {
            "user": 2,
            "first_name": "Vedúci",
            "last_name": "Strom",
            "school": 1,
            "year_of_graduation": 2019
        }
    },
    {
        "model": "account.emailaddress",
        "pk": 2,
        "fields": {
            "user": 2,
            "email": "veduci_stromu@strom.sk",
            "verified": true,
            "primary": true
        }
    },
    {
        "model": "user.User",
        "pk": 3,
        "fields": {
            "email": "veduci_krickov@strom.sk",
            "password": "pbkdf2_sha256$180000$NyzwabHNPn2K$sTirqoFPMkLZpnUHkCpzUFZnAsbGM7Bp2+EoN8sOuQA=",
            "is_superuser": false,
            "is_staff": true,
            "groups": [
                2
            ]
        }
    },
    {
        "model": "personal.Profile",
        "pk": 3,
        "fields": {
            "user": 3,
            "first_name": "Vedúci",
            "last_name": "Kríčky",
            "school": 1,
            "year_of_graduation": 2024
        }
    },
    {
        "model": "account.emailaddress",
        "pk": 3,
        "fields": {
            "user": 3,
            "email": "veduci_krickov@strom.sk",
            "verified": true,
            "primary": true
        }
    },
    {
        "model": "user.User",
        "pk": 4,
        "fields": {
            "email": "ucastnik_strom@strom.sk",
            "password": "pbkdf2_sha256$180000$NyzwabHNPn2K$sTirqoFPMkLZpnUHkCpzUFZnAsbGM7Bp2+EoN8sOuQA=",
            "is_superuser": false,
            "is_staff": false
        }
    },
    {
        "model": "personal.Profile",
        "pk": 4,
        "fields": {
            "user": 4,
            "first_name": "Účastník",
            "last_name": "Strom",
            "school": "000598071",
            "year_of_graduation": 2025
        }
    },
    {
        "model": "account.emailaddress",
        "pk": 4,
        "fields": {
            "user": 4,
            "email": "ucastnik_strom@strom.sk",
            "verified": true,
            "primary": true
        }
    },
    {
        "model": "user.User",
        "pk": 5,
        "fields": {
            "email": "ucastnik_matik@strom.sk",
            "password": "pbkdf2_sha256$180000$NyzwabHNPn2K$sTirqoFPMkLZpnUHkCpzUFZnAsbGM7Bp2+EoN8sOuQA=",
            "is_superuser": false,
            "is_staff": false
        }
    },
    {
        "model": "personal.Profile",
        "pk": 5,
        "fields": {
            "user": 5,
            "first_name": "Účastník",
            "last_name": "Matik",
            "school": "000598071",
            "year_of_graduation": 2028
        }
    },
    {
        "model": "account.emailaddress",
        "pk": 5,
        "fields": {
            "user": 5,
            "email": "ucastnik_matik@strom.sk",
            "verified": true,
            "primary": true
        }
    },
    {
        "model": "user.User",
        "pk": 6,
        "fields": {
            "email": "ucastnik_malynar@strom.sk",
            "password": "pbkdf2_sha256$180000$NyzwabHNPn2K$sTirqoFPMkLZpnUHkCpzUFZnAsbGM7Bp2+EoN8sOuQA=",
            "is_superuser": false,
            "is_staff": false
        }
    },
    {
        "model": "personal.Profile",
        "pk": 6,
        "fields": {
            "user": 6,
            "first_name": "Účastník",
            "last_name": "Malynár",
            "school": "000598071",
            "year_of_graduation": 2031
        }
    },
    {
        "model": "account.emailaddress",
        "pk": 6,
        "fields": {
            "user": 6,
            "email": "ucastnik_malynar@strom.sk",
            "verified": true,
            "primary": true
        }
    },
    {
        "model": "user.User",
        "pk": 7,
        "fields": {
            "email": "nahodny_vysokoskolak@strom.sk",
            "password": "pbkdf2_sha256$180000$NyzwabHNPn2K$sTirqoFPMkLZpnUHkCpzUFZnAsbGM7Bp2+EoN8sOuQA=",
            "is_superuser": false,
            "is_staff": false
        }
    },
    {
        "model": "personal.Profile",
        "pk": 7,
        "fields": {
            "user": 7,
            "first_name": "Náhodný",
            "last_name": "Vysokoškolák",
            "school": 1,
            "year_of_graduation": 2015
        }
    },
    {
        "model": "account.emailaddress",
        "pk": 7,
        "fields": {
            "user": 7,
            "email": "nahodny_vysokoskolak@strom.sk",
            "verified": true,
            "primary": true
        }
    }
]
